parameterizable/__init__.py
parameterizable/dict_sorter.py
parameterizable/json_processor.py
parameterizable/not_picklable.py
parameterizable/parameterizable.py
parameterizable-0.105.2.dist-info/METADATA
parameterizable-0.105.2.dist-info/WHEEL
parameterizable-0.105.2.dist-info/licenses/LICENSE
parameterizable-0.105.2.dist-info/RECORD
